[
  {
    "line": 3,
    "elements": [
      {
        "line": 5,
        "name": "",
        "description": "",
        "type": "background",
        "keyword": "Background",
        "steps": [
          {
            "result": {
              "duration": 389206277,
              "status": "passed"
            },
            "line": 6,
            "name": "I am on login page",
            "match": {
              "location": "LoginPageSD.setLoginPage()"
            },
            "keyword": "Given "
          }
        ]
      },
      {
        "before": [
          {
            "result": {
              "duration": 4919538549,
              "status": "passed"
            },
            "match": {
              "location": "SharedSd.setUp()"
            }
          }
        ],
        "line": 9,
        "name": "Verify invalid login from login page",
        "description": "",
        "id": "hubspot-page-feature;verify-invalid-login-from-login-page",
        "after": [
          {
            "result": {
              "duration": 176517087,
              "status": "passed"
            },
            "match": {
              "location": "SharedSd.tearDown(Scenario)"
            }
          }
        ],
        "type": "scenario",
        "keyword": "Scenario",
        "steps": [
          {
            "result": {
              "duration": 4851479788,
              "status": "passed"
            },
            "line": 10,
            "name": "I enter ademk@gmail.com into email field on the login page",
            "match": {
              "arguments": [
                {
                  "val": "ademk@gmail.com",
                  "offset": 8
                },
                {
                  "val": "email",
                  "offset": 29
                }
              ],
              "location": "LoginPageSD.enterDataIntoEmailAddress(String,String)"
            },
            "keyword": "When "
          },
          {
            "result": {
              "duration": 153002723,
              "status": "passed"
            },
            "line": 11,
            "name": "I enter abcd123 into password field on the login page",
            "match": {
              "arguments": [
                {
                  "val": "abcd123",
                  "offset": 8
                },
                {
                  "val": "password",
                  "offset": 21
                }
              ],
              "location": "LoginPageSD.enterDataIntoEmailAddress(String,String)"
            },
            "keyword": "And "
          },
          {
            "result": {
              "duration": 241640009,
              "status": "passed"
            },
            "line": 12,
            "name": "I click on login button on login page",
            "match": {
              "location": "LoginPageSD.clicklOnLoginButton()"
            },
            "keyword": "And "
          },
          {
            "result": {
              "duration": 1183854479,
              "status": "passed"
            },
            "line": 13,
            "name": "I verify invalid login message on sign in page",
            "match": {
              "location": "LoginPageSD.verifyLoginInErrorMessage()"
            },
            "keyword": "Then "
          }
        ],
        "tags": [
          {
            "line": 8,
            "name": "@login"
          }
        ]
      }
    ],
    "name": "HubSpot page feature",
    "description": "",
    "id": "hubspot-page-feature",
    "keyword": "Feature",
    "uri": "Hubspot.feature",
    "tags": [
      {
        "line": 1,
        "name": "@web"
      }
    ]
  }
]